Metadata-Version: 2.1
Name: anonymization-tool
Version: 0.1.2
Summary: Anonymization Tool
Home-page: https://github.com/joeytxy/anonymization_tool
Author: Joey Tan Xin Yi
Author-email: joeytxy0706@gmail.com
License: MIT
Keywords: anonymization tool
